201803/td4/define_opcode.v

`define OP_MOV_A_IM 4'b0011
`define OP_MOV_B_IM 4'b0111
`define OP_MOV_A_B  4'b0001
`define OP_MOV_B_A  4'b0100
`define OP_ADD_A_IM 4'b0000
`define OP_ADD_B_IM 4'b0101
`define OP_IN_A     4'b0010
`define OP_IN_B     4'b0110
`define OP_OUT_IM   4'b1011
`define OP_OUT_B    4'b1001
`define OP_JMP_IM   4'b1111
`define OP_JNC_IM   4'b1110

201803/td4/rom.v
`include "define_opcode.v"

module ROM(
    input[3:0] address,
    output reg [7:0] dout
);
    // JNCテスト
    // 15-> PC=3, 14-> PC=4
    // always @(*)
    //     case (address)
    //     0: dout <= { `OP_MOV_A_IM , 4'b1110 }; 
    //     1: dout <= { `OP_ADD_A_IM , 4'b0001 };
    //     2: dout <= { `OP_JNC_IM   , 4'b0100 };
    //     3: dout <= { `OP_JMP_IM   , 4'b0011 };
    //     4: dout <= { `OP_JMP_IM   , 4'b0100 };
    //     default: dout <= 8'bxxxxxxxx;
    // endcase
    
    // ADD,MOVテスト
    always @(*)
        case (address)
        0: dout <= {`OP_MOV_A_IM , 4'b0000 }; // a = b0000
        1: dout <= {`OP_ADD_A_IM , 4'b1010 }; // a = b1010
        2: dout <= {`OP_MOV_B_IM , 4'b0100 }; // b = b0100
        3: dout <= {`OP_ADD_B_IM , 4'b0001 }; // b = b0101
        4: dout <= {`OP_MOV_A_B  , 4'b0000 }; // a = b0101
        5: dout <= {`OP_JMP_IM   , 4'b0101 };
        default: dout <= 8'bxxxxxxxx;
    endcase
    
endmodule

201803/td4/adder.v
module ADDER(
    input [3:0] a,
    input [3:0] b,
    output [3:0] out,
    output carry_out
);
    assign {carry_out,out} = a + b;
endmodule

201803/td4/selector.v
module SELECTOR(
    input [3:0] in0,
    input [3:0] in1,
    input [3:0] in2,
    input [3:0] in3,
    input [1:0] select,
    output [3:0] out
);
    assign out = select == 0 ? in0 :
        select == 1 ? in1 : 
        select == 2 ? in2 :
        in3 ;
endmodule

201803/td4/decoder.v
`include "define_opcode.v"

module DECODER(
    input wire [3:0] opcode,
    input wire c_flag,
    output reg [1:0] select,
    output reg [3:0] load
);

    always @(*) begin
        case(opcode)
            `OP_MOV_A_IM:
                {load, select}  <= { 4'b0001, 2'b11 };   
            `OP_MOV_B_IM:
                {load, select}  <= { 4'b0010, 2'b11 };
            `OP_MOV_A_B:
                {load, select}  <= { 4'b0001, 2'b01 };
            `OP_MOV_B_A:
                {load, select}  <= { 4'b0010, 2'b00 };
            `OP_ADD_A_IM:
                {load, select}  <= { 4'b0001, 2'b00 };
            `OP_ADD_B_IM:
                {load, select}  <= { 4'b0010, 2'b01 };
            `OP_IN_A:
                {load, select}  <= { 4'b0001, 2'b10 };
            `OP_IN_B:
                {load, select}  <= { 4'b0010, 2'b10 };
            `OP_OUT_IM:
                {load, select}  <= { 4'b0100, 2'b11 };
            `OP_OUT_B:
                {load, select}  <= { 4'b0100, 2'b01 };
            `OP_JMP_IM:
                {load, select}  <= { 4'b1000, 2'b11 };
            `OP_JNC_IM:
                {load, select}  <= c_flag ?
                    {4'b0000, 2'b00 }:  // don't jump
                    {4'b1000, 2'b11 };  // jump
            default:
                {load, select}  = 6'b000000;
        endcase
    end

endmodule

module DECODER_TEST();
    reg [4:0] opcode_cflag;
    wire [1:0] select;
    wire [3:0] load;
    integer i;
    wire [3:0]opcode;
    wire cflag;

    assign {opcode,cflag} = opcode_cflag;

    DECODER unit1(opcode,c_flag,select,load);

    initial begin
        opcode_cflag = 0;
        for(i=0;i<32;i=i+1) begin
            #100
            // $display("%d,%d,%d,%d,%d | %d,%d,%d,%d,%d,%d",
            //     opcode[3],opcode[2],opcode[1],opcode[0],cflag,
            //     select_b,select_a,load[3],load[2],load[1],load[0]);
            opcode_cflag = opcode_cflag + 1;
        end
        $finish;
    end
endmodule

201803/td4/dff.v
module DFF(
    input [3:0] d,
    input enable,
    input reset,
    input clk,
    output [3:0] q
);
    reg [3:0] q;

    always @(posedge reset or posedge clk)
        q <= reset ? 0 : (enable ? d : q);
endmodule

201803/td4/cpu.v
module CPU(
    input reset,
    input clk
);
    wire [3:0]alu_out;
    wire [3:0]load;
    wire [1:0]select;
    wire [3:0]reg_a_out;
    wire [3:0]reg_b_out;
    wire [3:0]reg_c_out;
    wire [3:0]reg_d_out;
    wire [3:0]reg_1_out;
    wire [3:0]alu_in;
    wire [7:0]rom_out;
    wire [3:0]opcode;
    wire [3:0]imm;
    wire carry_out;
    wire [3:0]pc_next;
    
    DFF reg_a(alu_out,load[0],reset,clk,reg_a_out);
    DFF reg_b(alu_out,load[1],reset,clk,reg_b_out);
    DFF reg_c(alu_out,load[2],reset,clk,reg_c_out);
    DFF reg_d(pc_next,   1'b1,reset,clk,reg_d_out);
    DFF reg_1({3'b000,carry_out},1'b1,reset,clk,reg_1_out);

    assign pc_next = load[3] ? alu_out : reg_d_out + 4'b1;

    DECODER decoder(opcode,reg_1_out[0],select,load);

    SELECTOR selector(reg_a_out,reg_b_out,4'b0101,4'b0000,select,alu_in);
    ADDER alu(alu_in,imm,alu_out,carry_out);
    ROM rom(reg_d_out,rom_out);
    
    assign {opcode,imm} = rom_out;
endmodule

module CPU_TEST();
    reg reset;
    reg clk;
    integer i;

    CPU cpu(reset,clk);

    always #100 begin
        clk = ~clk;
        $monitor("a=%04b,b=%04b,out=%04b,pc=%04b"
                                ,cpu.reg_a_out
                                ,cpu.reg_b_out
                                ,cpu.reg_c_out
                                ,cpu.reg_d_out);
    end


    initial begin
        $dumpfile("out.vcd");
        $dumpvars(0,cpu);

        clk = 0;
        reset = 0;
        #1
        reset = 1;
        #1
        reset = 0;

        #3000
        $finish;
    end
endmodule

201803/td4/out.vcd
$date
	Thu Mar 29 19:41:58 2018
$end
$version
	Icarus Verilog
$end
$timescale
	1s
$end
$scope module CPU_TEST $end
$scope module cpu $end
$var wire 1 ! clk $end
$var wire 1 " reset $end
$var wire 2 # select [1:0] $end
$var wire 8 $ rom_out [7:0] $end
$var wire 4 % reg_d_out [3:0] $end
$var wire 4 & reg_c_out [3:0] $end
$var wire 4 ' reg_b_out [3:0] $end
$var wire 4 ( reg_a_out [3:0] $end
$var wire 4 ) reg_1_out [3:0] $end
$var wire 4 * pc_next [3:0] $end
$var wire 4 + opcode [3:0] $end
$var wire 4 , load [3:0] $end
$var wire 4 - imm [3:0] $end
$var wire 1 . carry_out $end
$var wire 4 / alu_out [3:0] $end
$var wire 4 0 alu_in [3:0] $end
$scope module alu $end
$var wire 4 1 b [3:0] $end
$var wire 4 2 out [3:0] $end
$var wire 1 . carry_out $end
$var wire 4 3 a [3:0] $end
$upscope $end
$scope module decoder $end
$var wire 1 4 c_flag $end
$var wire 4 5 opcode [3:0] $end
$var reg 4 6 load [3:0] $end
$var reg 2 7 select [1:0] $end
$upscope $end
$scope module reg_1 $end
$var wire 1 ! clk $end
$var wire 4 8 d [3:0] $end
$var wire 1 9 enable $end
$var wire 1 " reset $end
$var reg 4 : q [3:0] $end
$upscope $end
$scope module reg_a $end
$var wire 1 ! clk $end
$var wire 4 ; d [3:0] $end
$var wire 1 < enable $end
$var wire 1 " reset $end
$var reg 4 = q [3:0] $end
$upscope $end
$scope module reg_b $end
$var wire 1 ! clk $end
$var wire 4 > d [3:0] $end
$var wire 1 ? enable $end
$var wire 1 " reset $end
$var reg 4 @ q [3:0] $end
$upscope $end
$scope module reg_c $end
$var wire 1 ! clk $end
$var wire 4 A d [3:0] $end
$var wire 1 B enable $end
$var wire 1 " reset $end
$var reg 4 C q [3:0] $end
$upscope $end
$scope module reg_d $end
$var wire 1 ! clk $end
$var wire 4 D d [3:0] $end
$var wire 1 E enable $end
$var wire 1 " reset $end
$var reg 4 F q [3:0] $end
$upscope $end
$scope module rom $end
$var wire 4 G address [3:0] $end
$var reg 8 H dout [7:0] $end
$upscope $end
$scope module selector $end
$var wire 4 I in0 [3:0] $end
$var wire 4 J in1 [3:0] $end
$var wire 4 K in2 [3:0] $end
$var wire 4 L in3 [3:0] $end
$var wire 2 M select [1:0] $end
$var wire 4 N out [3:0] $end
$upscope $end
$upscope $end
$upscope $end
$enddefinitions $end
#0
$dumpvars
bx N
bx M
b0 L
b101 K
bx J
bx I
bx H
bx G
bx F
1E
bx D
bx C
xB
bx A
bx @
x?
bx >
bx =
x<
bx ;
bx :
19
b0x 8
bx 7
bx 6
bx 5
x4
bx 3
bx 2
bx 1
bx 0
bx /
x.
bx -
bx ,
bx +
bx *
bx )
bx (
bx '
bx &
bx %
bx $
bx #
0"
0!
$end
#1
b0 /
b0 2
b0 ;
b0 >
b0 A
b0 8
0.
b11 +
b11 5
b0 -
b0 1
b110000 $
b110000 H
b1 *
b1 D
0B
0?
1<
b1 ,
b1 6
b11 #
b11 7
b11 M
b0 0
b0 3
b0 N
04
b0 (
b0 =
b0 I
b0 '
b0 @
b0 J
b0 &
b0 C
b0 %
b0 F
b0 G
b0 )
b0 :
1"
#2
0"
#100
b0 #
b0 7
b0 M
b1010 /
b1010 2
b1010 ;
b1010 >
b1010 A
b0 +
b0 5
b1010 -
b1010 1
b1010 $
b1010 H
b10 *
b10 D
b1 %
b1 F
b1 G
1!
#200
0!
#300
1?
0<
b10 ,
b10 6
b11 #
b11 7
b11 M
b111 +
b111 5
b100 -
b100 1
b1110100 $
b1110100 H
b100 /
b100 2
b100 ;
b100 >
b100 A
b0 8
0.
b0 0
b0 3
b0 N
b11 *
b11 D
b1010 (
b1010 =
b1010 I
b10 %
b10 F
b10 G
1!
#400
0!
#500
b100 0
b100 3
b100 N
b1 #
b1 7
b1 M
b101 /
b101 2
b101 ;
b101 >
b101 A
b101 +
b101 5
b1 -
b1 1
b1010001 $
b1010001 H
b100 *
b100 D
b11 %
b11 F
b11 G
b100 '
b100 @
b100 J
1!
#600
0!
#700
0?
1<
b1 ,
b1 6
b1 +
b1 5
b0 -
b0 1
b10000 $
b10000 H
b101 /
b101 2
b101 ;
b101 >
b101 A
b101 0
b101 3
b101 N
b101 *
b101 D
b101 '
b101 @
b101 J
b100 %
b100 F
b100 G
1!
#800
0!
#900
b0 0
b0 3
b0 N
0<
b1000 ,
b1000 6
b11 #
b11 7
b11 M
b101 /
b101 2
b101 ;
b101 >
b101 A
b1111 +
b1111 5
b101 -
b101 1
b11110101 $
b11110101 H
b101 *
b101 D
b101 %
b101 F
b101 G
b101 (
b101 =
b101 I
1!
