201803/verilog010/main.v
module RSFF(r,s,clk,q,q_b);
    input r,s,clk;
    output q,q_b;
    reg q;

    assign q_b = ~q;

    always @(posedge clk)
        case({r,s})
            1: q <= 1;
            2: q <= 0;
            3: q <= 1'bx;
        endcase
endmodule

`timescale 1ns/1ns

module TESTBENCH;
    reg r,s,clk;
    wire out1,out2;
    parameter STEP = 50;

    RSFF u1(r,s,clk,out1,out2);

    always #(STEP/2) clk = ~clk;

    initial begin
        $dumpfile("out.vcd");
        $dumpvars(0,u1);

        clk=0;
        r=0;
        s=0;
        #100

        r=1;
        s=0;
        #100

        r=0;
        s=1;
        #100

        r=1;
        s=0;
        #100

        r=1;
        s=1;
        #100

        r=0;
        s=0;
        #100

        r=0;
        s=1;
        #100

        $finish;
    end
endmodule

201803/verilog010/out.vcd
$date
	Mon Mar 26 01:07:41 2018
$end
$version
	Icarus Verilog
$end
$timescale
	1ns
$end
$scope module TESTBENCH $end
$scope module u1 $end
$var wire 1 ! clk $end
$var wire 1 " q_b $end
$var wire 1 # r $end
$var wire 1 $ s $end
$var reg 1 % q $end
$upscope $end
$upscope $end
$enddefinitions $end
#0
$dumpvars
x%
0$
0#
x"
0!
$end
#25
1!
#50
0!
#75
1!
#100
0!
1#
#125
1"
0%
1!
#150
0!
#175
1!
#200
0!
1$
0#
#225
0"
1%
1!
#250
0!
#275
1!
#300
0!
0$
1#
#325
1"
0%
1!
#350
0!
#375
1!
#400
0!
1$
#425
x"
x%
1!
#450
0!
#475
1!
#500
0!
0$
0#
#525
1!
#550
0!
#575
1!
#600
0!
1$
#625
0"
1%
1!
