201804/verilog000/main.v
module TEST_BENCH();
    reg out;

    initial begin
        $dumpfile("a.vcd");
        $dumpvars(0,out);
        
        #00000000 out=1;
        #00973140 out=0;
        #00001812 out=1;
        #00001808 out=0;
        #00009044 out=1;
        #00001812 out=0;
        #00003616 out=1;
        #00982528 out=0;
        #00001808 out=1;
        #00001808 out=0;
        #00009048 out=1;
        #00001808 out=0;
        #00003620 out=1;
        #00982412 out=0;
        #00001812 out=1;
        #00001808 out=0;

        $finish;
    end
endmodule

201804/verilog000/a.vcd
$date
	Wed Apr 18 00:11:49 2018
$end
$version
	Icarus Verilog
$end
$timescale
	1s
$end
$scope module TEST_BENCH $end
$var reg 1 ! out $end
$upscope $end
$enddefinitions $end
#0
$dumpvars
1!
$end
#973140
0!
#974952
1!
#976760
0!
#985804
1!
#987616
0!
#991232
1!
#1973760
0!
#1975568
1!
#1977376
0!
#1986424
1!
#1988232
0!
#1991852
1!
#2974264
0!
#2976076
1!
#2977884
0!
