201803/verilog005/main.v
module SEL(a,b,c,d,sel,out);
    input a,b,c,d;
    input [1:0] sel;
    output out;

    assign out = FUNC(a,b,c,d,sel);

    function FUNC;
        input a,b,c,d;
        input [1:0] sel;

        if( sel == 0)
            FUNC = a;
        else if(sel==1)
            FUNC = b;
        else if(sel==2)
            FUNC = c;
        else
            FUNC = d;
    endfunction
endmodule

module TESTBENCH;
    reg [3:0]in;
    reg [1:0]sel;
    wire out;
    integer i,j;

    SEL u1 (in[0],in[1],in[2],in[3],sel,out);

    initial begin
        $dumpfile("out.vcd");
        $dumpvars(0,u1);

        in = 0;
        for(i=0;i<64;i++) begin
            in += 1;
            sel = 0;
            for(j=0;j<4;j++) begin
                #100
                sel += 1;
            end
        end

        $finish;
    end
endmodule

201803/verilog005/out.vcd
$date
	Sun Mar 25 14:12:32 2018
$end
$version
	Icarus Verilog
$end
$timescale
	1s
$end
$scope module TESTBENCH $end
$scope module u1 $end
$var wire 1 ! a $end
$var wire 1 " b $end
$var wire 1 # c $end
$var wire 1 $ d $end
$var wire 2 % sel [1:0] $end
$var wire 1 & out $end
$scope function FUNC $end
$var reg 1 ' FUNC $end
$var reg 1 ( a $end
$var reg 1 ) b $end
$var reg 1 * c $end
$var reg 1 + d $end
$var reg 2 , sel [1:0] $end
$upscope $end
$upscope $end
$upscope $end
$enddefinitions $end
#0
$dumpvars
b0 ,
0+
0*
0)
1(
1'
1&
b0 %
0$
0#
0"
1!
$end
#100
0&
0'
b1 ,
b1 %
#200
b10 ,
b10 %
#300
b11 ,
b11 %
#400
1)
0(
0!
1"
0&
0'
b0 ,
b0 %
#500
1&
1'
b1 ,
b1 %
#600
0&
0'
b10 ,
b10 %
#700
b11 ,
b11 %
#800
1&
1'
1(
1!
b0 ,
b0 %
#900
b1 ,
b1 %
#1000
0&
0'
b10 ,
b10 %
#1100
b11 ,
b11 %
#1200
1*
0)
0(
0!
0"
1#
0&
0'
b0 ,
b0 %
#1300
b1 ,
b1 %
#1400
1&
1'
b10 ,
b10 %
#1500
0&
0'
b11 ,
b11 %
#1600
1&
1'
1(
1!
b0 ,
b0 %
#1700
0&
0'
b1 ,
b1 %
#1800
1&
1'
b10 ,
b10 %
#1900
0&
0'
b11 ,
b11 %
#2000
1)
0(
0!
1"
0&
0'
b0 ,
b0 %
#2100
1&
1'
b1 ,
b1 %
#2200
b10 ,
b10 %
#2300
0&
0'
b11 ,
b11 %
#2400
1&
1'
1(
1!
b0 ,
b0 %
#2500
b1 ,
b1 %
#2600
b10 ,
b10 %
#2700
0&
0'
b11 ,
b11 %
#2800
1+
0*
0)
0(
0!
0"
0#
1$
0&
0'
b0 ,
b0 %
#2900
b1 ,
b1 %
#3000
b10 ,
b10 %
#3100
1&
1'
b11 ,
b11 %
#3200
1(
1!
1&
1'
b0 ,
b0 %
#3300
0&
0'
b1 ,
b1 %
#3400
b10 ,
b10 %
#3500
1&
1'
b11 ,
b11 %
#3600
0&
0'
1)
0(
0!
1"
b0 ,
b0 %
#3700
1&
1'
b1 ,
b1 %
#3800
0&
0'
b10 ,
b10 %
#3900
1&
1'
b11 ,
b11 %
#4000
1(
1!
1&
1'
b0 ,
b0 %
#4100
b1 ,
b1 %
#4200
0&
0'
b10 ,
b10 %
#4300
1&
1'
b11 ,
b11 %
#4400
0&
0'
1*
0)
0(
0!
0"
1#
b0 ,
b0 %
#4500
b1 ,
b1 %
#4600
1&
1'
b10 ,
b10 %
#4700
b11 ,
b11 %
#4800
1(
1!
1&
1'
b0 ,
b0 %
#4900
0&
0'
b1 ,
b1 %
#5000
1&
1'
b10 ,
b10 %
#5100
b11 ,
b11 %
#5200
0&
0'
1)
0(
0!
1"
b0 ,
b0 %
#5300
1&
1'
b1 ,
b1 %
#5400
b10 ,
b10 %
#5500
b11 ,
b11 %
#5600
1(
1!
1&
1'
b0 ,
b0 %
#5700
b1 ,
b1 %
#5800
b10 ,
b10 %
#5900
b11 ,
b11 %
#6000
0&
0'
0+
0*
0)
0(
0!
0"
0#
0$
b0 ,
b0 %
#6100
b1 ,
b1 %
#6200
b10 ,
b10 %
#6300
b11 ,
b11 %
#6400
1&
1'
1(
1!
b0 ,
b0 %
#6500
0&
0'
b1 ,
b1 %
#6600
b10 ,
b10 %
#6700
b11 ,
b11 %
#6800
1)
0(
0!
1"
0&
0'
b0 ,
b0 %
#6900
1&
1'
b1 ,
b1 %
#7000
0&
0'
b10 ,
b10 %
#7100
b11 ,
b11 %
#7200
1&
1'
1(
1!
b0 ,
b0 %
#7300
b1 ,
b1 %
#7400
0&
0'
b10 ,
b10 %
#7500
b11 ,
b11 %
#7600
1*
0)
0(
0!
0"
1#
0&
0'
b0 ,
b0 %
#7700
b1 ,
b1 %
#7800
1&
1'
b10 ,
b10 %
#7900
0&
0'
b11 ,
b11 %
#8000
1&
1'
1(
1!
b0 ,
b0 %
#8100
0&
0'
b1 ,
b1 %
#8200
1&
1'
b10 ,
b10 %
#8300
0&
0'
b11 ,
b11 %
#8400
1)
0(
0!
1"
0&
0'
b0 ,
b0 %
#8500
1&
1'
b1 ,
b1 %
#8600
b10 ,
b10 %
#8700
0&
0'
b11 ,
b11 %
#8800
1&
1'
1(
1!
b0 ,
b0 %
#8900
b1 ,
b1 %
#9000
b10 ,
b10 %
#9100
0&
0'
b11 ,
b11 %
#9200
1+
0*
0)
0(
0!
0"
0#
1$
0&
0'
b0 ,
b0 %
#9300
b1 ,
b1 %
#9400
b10 ,
b10 %
#9500
1&
1'
b11 ,
b11 %
#9600
1(
1!
1&
1'
b0 ,
b0 %
#9700
0&
0'
b1 ,
b1 %
#9800
b10 ,
b10 %
#9900
1&
1'
b11 ,
b11 %
#10000
0&
0'
1)
0(
0!
1"
b0 ,
b0 %
#10100
1&
1'
b1 ,
b1 %
#10200
0&
0'
b10 ,
b10 %
#10300
1&
1'
b11 ,
b11 %
#10400
1(
1!
1&
1'
b0 ,
b0 %
#10500
b1 ,
b1 %
#10600
0&
0'
b10 ,
b10 %
#10700
1&
1'
b11 ,
b11 %
#10800
0&
0'
1*
0)
0(
0!
0"
1#
b0 ,
b0 %
#10900
b1 ,
b1 %
#11000
1&
1'
b10 ,
b10 %
#11100
b11 ,
b11 %
#11200
1(
1!
1&
1'
b0 ,
b0 %
#11300
0&
0'
b1 ,
b1 %
#11400
1&
1'
b10 ,
b10 %
#11500
b11 ,
b11 %
#11600
0&
0'
1)
0(
0!
1"
b0 ,
b0 %
#11700
1&
1'
b1 ,
b1 %
#11800
b10 ,
b10 %
#11900
b11 ,
b11 %
#12000
1(
1!
1&
1'
b0 ,
b0 %
#12100
b1 ,
b1 %
#12200
b10 ,
b10 %
#12300
b11 ,
b11 %
#12400
0&
0'
0+
0*
0)
0(
0!
0"
0#
0$
b0 ,
b0 %
#12500
b1 ,
b1 %
#12600
b10 ,
b10 %
#12700
b11 ,
b11 %
#12800
1&
1'
1(
1!
b0 ,
b0 %
#12900
0&
0'
b1 ,
b1 %
#13000
b10 ,
b10 %
#13100
b11 ,
b11 %
#13200
1)
0(
0!
1"
0&
0'
b0 ,
b0 %
#13300
1&
1'
b1 ,
b1 %
#13400
0&
0'
b10 ,
b10 %
#13500
b11 ,
b11 %
#13600
1&
1'
1(
1!
b0 ,
b0 %
#13700
b1 ,
b1 %
#13800
0&
0'
b10 ,
b10 %
#13900
b11 ,
b11 %
#14000
1*
0)
0(
0!
0"
1#
0&
0'
b0 ,
b0 %
#14100
b1 ,
b1 %
#14200
1&
1'
b10 ,
b10 %
#14300
0&
0'
b11 ,
b11 %
#14400
1&
1'
1(
1!
b0 ,
b0 %
#14500
0&
0'
b1 ,
b1 %
#14600
1&
1'
b10 ,
b10 %
#14700
0&
0'
b11 ,
b11 %
#14800
1)
0(
0!
1"
0&
0'
b0 ,
b0 %
#14900
1&
1'
b1 ,
b1 %
#15000
b10 ,
b10 %
#15100
0&
0'
b11 ,
b11 %
#15200
1&
1'
1(
1!
b0 ,
b0 %
#15300
b1 ,
b1 %
#15400
b10 ,
b10 %
#15500
0&
0'
b11 ,
b11 %
#15600
1+
0*
0)
0(
0!
0"
0#
1$
0&
0'
b0 ,
b0 %
#15700
b1 ,
b1 %
#15800
b10 ,
b10 %
#15900
1&
1'
b11 ,
b11 %
#16000
1(
1!
1&
1'
b0 ,
b0 %
#16100
0&
0'
b1 ,
b1 %
#16200
b10 ,
b10 %
#16300
1&
1'
b11 ,
b11 %
#16400
0&
0'
1)
0(
0!
1"
b0 ,
b0 %
#16500
1&
1'
b1 ,
b1 %
#16600
0&
0'
b10 ,
b10 %
#16700
1&
1'
b11 ,
b11 %
#16800
1(
1!
1&
1'
b0 ,
b0 %
#16900
b1 ,
b1 %
#17000
0&
0'
b10 ,
b10 %
#17100
1&
1'
b11 ,
b11 %
#17200
0&
0'
1*
0)
0(
0!
0"
1#
b0 ,
b0 %
#17300
b1 ,
b1 %
#17400
1&
1'
b10 ,
b10 %
#17500
b11 ,
b11 %
#17600
1(
1!
1&
1'
b0 ,
b0 %
#17700
0&
0'
b1 ,
b1 %
#17800
1&
1'
b10 ,
b10 %
#17900
b11 ,
b11 %
#18000
0&
0'
1)
0(
0!
1"
b0 ,
b0 %
#18100
1&
1'
b1 ,
b1 %
#18200
b10 ,
b10 %
#18300
b11 ,
b11 %
#18400
1(
1!
1&
1'
b0 ,
b0 %
#18500
b1 ,
b1 %
#18600
b10 ,
b10 %
#18700
b11 ,
b11 %
#18800
0&
0'
0+
0*
0)
0(
0!
0"
0#
0$
b0 ,
b0 %
#18900
b1 ,
b1 %
#19000
b10 ,
b10 %
#19100
b11 ,
b11 %
#19200
1&
1'
1(
1!
b0 ,
b0 %
#19300
0&
0'
b1 ,
b1 %
#19400
b10 ,
b10 %
#19500
b11 ,
b11 %
#19600
1)
0(
0!
1"
0&
0'
b0 ,
b0 %
#19700
1&
1'
b1 ,
b1 %
#19800
0&
0'
b10 ,
b10 %
#19900
b11 ,
b11 %
#20000
1&
1'
1(
1!
b0 ,
b0 %
#20100
b1 ,
b1 %
#20200
0&
0'
b10 ,
b10 %
#20300
b11 ,
b11 %
#20400
1*
0)
0(
0!
0"
1#
0&
0'
b0 ,
b0 %
#20500
b1 ,
b1 %
#20600
1&
1'
b10 ,
b10 %
#20700
0&
0'
b11 ,
b11 %
#20800
1&
1'
1(
1!
b0 ,
b0 %
#20900
0&
0'
b1 ,
b1 %
#21000
1&
1'
b10 ,
b10 %
#21100
0&
0'
b11 ,
b11 %
#21200
1)
0(
0!
1"
0&
0'
b0 ,
b0 %
#21300
1&
1'
b1 ,
b1 %
#21400
b10 ,
b10 %
#21500
0&
0'
b11 ,
b11 %
#21600
1&
1'
1(
1!
b0 ,
b0 %
#21700
b1 ,
b1 %
#21800
b10 ,
b10 %
#21900
0&
0'
b11 ,
b11 %
#22000
1+
0*
0)
0(
0!
0"
0#
1$
0&
0'
b0 ,
b0 %
#22100
b1 ,
b1 %
#22200
b10 ,
b10 %
#22300
1&
1'
b11 ,
b11 %
#22400
1(
1!
1&
1'
b0 ,
b0 %
#22500
0&
0'
b1 ,
b1 %
#22600
b10 ,
b10 %
#22700
1&
1'
b11 ,
b11 %
#22800
0&
0'
1)
0(
0!
1"
b0 ,
b0 %
#22900
1&
1'
b1 ,
b1 %
#23000
0&
0'
b10 ,
b10 %
#23100
1&
1'
b11 ,
b11 %
#23200
1(
1!
1&
1'
b0 ,
b0 %
#23300
b1 ,
b1 %
#23400
0&
0'
b10 ,
b10 %
#23500
1&
1'
b11 ,
b11 %
#23600
0&
0'
1*
0)
0(
0!
0"
1#
b0 ,
b0 %
#23700
b1 ,
b1 %
#23800
1&
1'
b10 ,
b10 %
#23900
b11 ,
b11 %
#24000
1(
1!
1&
1'
b0 ,
b0 %
#24100
0&
0'
b1 ,
b1 %
#24200
1&
1'
b10 ,
b10 %
#24300
b11 ,
b11 %
#24400
0&
0'
1)
0(
0!
1"
b0 ,
b0 %
#24500
1&
1'
b1 ,
b1 %
#24600
b10 ,
b10 %
#24700
b11 ,
b11 %
#24800
1(
1!
1&
1'
b0 ,
b0 %
#24900
b1 ,
b1 %
#25000
b10 ,
b10 %
#25100
b11 ,
b11 %
#25200
0&
0'
0+
0*
0)
0(
0!
0"
0#
0$
b0 ,
b0 %
#25300
b1 ,
b1 %
#25400
b10 ,
b10 %
#25500
b11 ,
b11 %
#25600
b0 ,
b0 %
